often_util_project/__init__.py
often_util_project/utils/__init__.py
often_util_project/utils/date_utils.py
often_util_project/utils/ip_utils.py
often_util_project/utils/valid_utils.py
test_util_project-0.1.dist-info/LICENSE
test_util_project-0.1.dist-info/METADATA
test_util_project-0.1.dist-info/WHEEL
test_util_project-0.1.dist-info/top_level.txt
test_util_project-0.1.dist-info/RECORD
