Metadata-Version: 2.1
Name: test-util-project
Version: 0.1
Summary: A simple example package
Home-page: UNKNOWN
Author: liubo
Author-email: 
License: MIT
Platform: UNKNOWN
